model21cm/__init__.py
model21cm/io.py
model21cm/model.py
model21cm/parameter.py
model21cm/data/edges_data.csv
model21cm-1.0.0.dist-info/METADATA
model21cm-1.0.0.dist-info/RECORD
model21cm-1.0.0.dist-info/WHEEL
model21cm-1.0.0.dist-info/top_level.txt
